python_maze_generator/__init__.py
python_maze_generator/line_maze.py
python_maze_generator/multithreaded_maze.py
python_maze_generator/square_maze.py
python_maze_generator-1.0.3.dist-info/METADATA
python_maze_generator-1.0.3.dist-info/WHEEL
python_maze_generator-1.0.3.dist-info/top_level.txt
python_maze_generator-1.0.3.dist-info/RECORD
