Metadata-Version: 2.1
Name: python-maze-generator
Version: 1.0.3
Summary: Python PNG Maze Generator
Home-page: https://github.com/nattyboyme3/python-maze
Author: Nat Biggs
Author-email: nat.biggs@live.com
Project-URL: Bug Tracker, https://github.com/nattyboyme3/python-maze/issues
Classifier: Programming Language :: Python :: 3
Classifier: License :: OSI Approved :: MIT License
Classifier: Operating System :: OS Independent
Requires-Python: >=3.6
Requires-Dist: colorama (>=0.4.4)
Requires-Dist: Pillow (>=8.4.0)
Requires-Dist: anytree (>=2.8.0)
